aws_idc_list_user_permissions/__init__.py
aws_idc_list_user_permissions/aws_idc_list_user_permissions.py
aws_idc_list_user_permissions/file_output_utils.py
aws_idc_list_user_permissions/list_user_permissions.py
aws_idc_list_user_permissions/list_utils.py
aws_idc_list_user_permissions-0.2.0.dist-info/METADATA
aws_idc_list_user_permissions-0.2.0.dist-info/WHEEL
aws_idc_list_user_permissions-0.2.0.dist-info/entry_points.txt
aws_idc_list_user_permissions-0.2.0.dist-info/RECORD
