Metadata-Version: 2.1
Name: aws-idc-list-user-permissions
Version: 0.2.0
Summary: 
Author: Keith Rozario
Author-email: keithjosephrozario@gmail.com
Requires-Python: >=3.9,<4.0
Classifier: Programming Language :: Python :: 3
Classifier: Programming Language :: Python :: 3.9
Classifier: Programming Language :: Python :: 3.10
Classifier: Programming Language :: Python :: 3.11
Classifier: Programming Language :: Python :: 3.12
Requires-Dist: boto3 (>=1.34.91,<2.0.0)
Requires-Dist: click (>=8.1.7,<9.0.0)
